st_dif/__init__.py
st_dif/cmgraph.py
st_dif/data_utils.py
st_dif/train_test_utils.py
st_dif/vis_utils.py
st_dif/models/__init__.py
st_dif/models/sten.py
st_dif/models/temporal_only.py
st_dif-0.1.2.dist-info/licenses/LICENSE
st_dif-0.1.2.dist-info/METADATA
st_dif-0.1.2.dist-info/WHEEL
st_dif-0.1.2.dist-info/top_level.txt
st_dif-0.1.2.dist-info/RECORD
