Metadata-Version: 2.4
Name: st_dif
Version: 0.1.2
Summary: A library for crowdflow prediction!
Author-email: Vivian Wong <vivian.wong@ufl.edu>
Requires-Python: >=3.10
License-File: LICENSE
Requires-Dist: torch>=2.5
Requires-Dist: numpy>=2.0
Requires-Dist: pandas==2.2.3
Requires-Dist: torch_geometric
Requires-Dist: torch_geometric_temporal
Requires-Dist: torch_scatter
Requires-Dist: torch_sparse
Requires-Dist: matplotlib
Requires-Dist: seaborn
Requires-Dist: opencv-python
Requires-Dist: tqdm
Requires-Dist: configparser
Requires-Dist: argparse
Requires-Dist: ipykernel
Provides-Extra: dev
Requires-Dist: pytest>=7.0; extra == "dev"
Requires-Dist: black>=22.0; extra == "dev"
Requires-Dist: mypy>=1.0; extra == "dev"
Dynamic: license-file
